winzy_zenmode/__init__.py
winzy_zenmode/ontop.py
winzy_zenmode-0.1.0.dist-info/LICENSE
winzy_zenmode-0.1.0.dist-info/METADATA
winzy_zenmode-0.1.0.dist-info/WHEEL
winzy_zenmode-0.1.0.dist-info/entry_points.txt
winzy_zenmode-0.1.0.dist-info/top_level.txt
winzy_zenmode-0.1.0.dist-info/RECORD
