Metadata-Version: 2.2
Name: winzy-zenmode
Version: 0.1.0
Summary: Zenmode stay focussed with only the priority windows and nothing else.
Author: Sukhbinder Singh
License: Apache-2.0
Project-URL: Homepage, https://github.com/sukhbinder/winzy-zenmode
Project-URL: Changelog, https://github.com/sukhbinder/winzy-zenmode/releases
Project-URL: Issues, https://github.com/sukhbinder/winzy-zenmode/issues
Project-URL: CI, https://github.com/sukhbinder/winzy-zenmode/actions
Classifier: License :: OSI Approved :: Apache Software License
License-File: LICENSE
Requires-Dist: winzy
Provides-Extra: test
Requires-Dist: pytest; extra == "test"
